{
	"node": "n8n-nodes-base.awsTextract",
	"nodeVersion": "1.0",
	"codexVersion": "1.0",
	"categories": [
		"Utility"
	],
	"resources": {
		"credentialDocumentation": [
			{
				"url": "https://docs.n8n.io/credentials/aws"
			}
		],
		"primaryDocumentation": [
			{
				"url": "https://docs.n8n.io/nodes/n8n-nodes-base.awsTextract/"
			}
		],
		"generic": [
			{
				"label": "7 no-code workflow automations for Amazon Web Services",
				"url": "https://n8n.io/blog/aws-workflow-automation/"
			}
		]
	}
}