{
    "type": "object",
    "properties": {
        "gid": {
            "type": "string"
        },
        "projects": {
            "type": "array",
            "items": {
                "type": "object",
                "properties": {
                    "gid": {
                        "type": "string"
                    },
                    "resource_type": {
                        "type": "string"
                    },
                    "name": {
                        "type": "string"
                    }
                },
                "required": [
                    "gid",
                    "resource_type",
                    "name"
                ]
            }
        },
        "num_likes": {
            "type": "integer"
        },
        "num_hearts": {
            "type": "integer"
        },
        "workspace": {
            "type": "object",
            "properties": {
                "gid": {
                    "type": "string"
                },
                "resource_type": {
                    "type": "string"
                },
                "name": {
                    "type": "string"
                }
            },
            "required": [
                "gid",
                "resource_type",
                "name"
            ]
        },
        "tags": {
            "type": "array",
            "items": {
                "type": "object",
                "properties": {
                    "gid": {
                        "type": "string"
                    },
                    "resource_type": {
                        "type": "string"
                    },
                    "name": {
                        "type": "string"
                    }
                },
                "required": [
                    "gid",
                    "resource_type",
                    "name"
                ]
            }
        },
        "start_at": {
            "type": "null"
        },
        "resource_subtype": {
            "type": "string"
        },
        "due_at": {
            "type": "null"
        },
        "assignee_status": {
            "type": "string"
        },
        "completed": {
            "type": "boolean"
        },
        "actual_time_minutes": {
            "type": "integer"
        },
        "notes": {
            "type": "string"
        },
        "name": {
            "type": "string"
        },
        "modified_at": {
            "type": "string"
        },
        "created_at": {
            "type": "string"
        },
        "resource_type": {
            "type": "string"
        },
        "assignee": {
            "type": "object",
            "properties": {
                "gid": {
                    "type": "string"
                },
                "resource_type": {
                    "type": "string"
                },
                "name": {
                    "type": "string"
                }
            },
            "required": [
                "gid",
                "resource_type",
                "name"
            ]
        },
        "liked": {
            "type": "boolean"
        },
        "hearted": {
            "type": "boolean"
        },
        "followers": {
            "type": "array",
            "items": {
                "type": "object",
                "properties": {
                    "gid": {
                        "type": "string"
                    },
                    "resource_type": {
                        "type": "string"
                    },
                    "name": {
                        "type": "string"
                    }
                },
                "required": [
                    "gid",
                    "resource_type",
                    "name"
                ]
            }
        },
        "memberships": {
            "type": "array",
            "items": {
                "type": "object",
                "properties": {
                    "project": {
                        "type": "object",
                        "properties": {
                            "gid": {
                                "type": "string"
                            },
                            "resource_type": {
                                "type": "string"
                            },
                            "name": {
                                "type": "string"
                            }
                        },
                        "required": [
                            "gid",
                            "resource_type",
                            "name"
                        ]
                    },
                    "section": {
                        "type": "object",
                        "properties": {
                            "gid": {
                                "type": "string"
                            },
                            "resource_type": {
                                "type": "string"
                            },
                            "name": {
                                "type": "string"
                            }
                        },
                        "required": [
                            "gid",
                            "resource_type",
                            "name"
                        ]
                    }
                },
                "required": [
                    "project",
                    "section"
                ]
            }
        },
        "permalink_url": {
            "type": "string"
        },
        "custom_fields": {
            "type": "array",
            "items": {
                "type": "object",
                "properties": {
                    "gid": {
                        "type": "string"
                    },
                    "resource_type": {
                        "type": "string"
                    },
                    "resource_subtype": {
                        "type": "string"
                    },
                    "type": {
                        "type": "string"
                    },
                    "name": {
                        "type": "string"
                    },
                    "enabled": {
                        "type": "boolean"
                    },
                    "precision": {
                        "type": "integer"
                    },
                    "enum_options": {
                        "type": "array",
                        "items": {
                            "type": "object",
                            "properties": {
                                "gid": {
                                    "type": "string"
                                },
                                "resource_type": {
                                    "type": "string"
                                },
                                "enabled": {
                                    "type": "boolean"
                                },
                                "name": {
                                    "type": "string"
                                },
                                "color": {
                                    "type": "string"
                                }
                            },
                            "required": [
                                "gid",
                                "resource_type",
                                "enabled",
                                "name",
                                "color"
                            ]
                        }
                    }
                },
                "required": [
                    "gid",
                    "resource_type",
                    "created_by",
                    "resource_subtype",
                    "type",
                    "name",
                    "enabled",
                    "display_value"
                ]
            }
        }
    },
    "version": 1
}
