{
    "type": "object",
    "properties": {
        "id": {
            "type": "integer"
        },
        "name": {
            "type": "string"
        },
        "slug": {
            "type": "string"
        },
        "email": {
            "type": "string"
        },
        "createdAt": {
            "type": "string"
        },
        "updatedAt": {
            "type": "string"
        },
        "_links": {
            "type": "object",
            "properties": {
                "self": {
                    "type": "object",
                    "properties": {
                        "href": {
                            "type": "string"
                        }
                    },
                    "required": [
                        "href"
                    ]
                },
                "folders": {
                    "type": "object",
                    "properties": {
                        "href": {
                            "type": "string"
                        }
                    },
                    "required": [
                        "href"
                    ]
                },
                "fields": {
                    "type": "object",
                    "properties": {
                        "href": {
                            "type": "string"
                        }
                    },
                    "required": [
                        "href"
                    ]
                }
            },
            "required": [
                "self",
                "folders",
                "fields"
            ]
        }
    },
    "required": [
        "id",
        "name",
        "slug",
        "email",
        "createdAt",
        "updatedAt",
        "_links"
    ],
    "version": 1
}
