{
	"Start Tutorial": [{ "triggered": true }],
	"1. The Kitchen (GET /menu)": [{ "body": {}, "headers": {}, "query": {} }],
	"2. The Kitchen (GET /order)": [
		{ "body": {}, "headers": {}, "query": { "extra_cheese": "true" } }
	],
	"3. The Kitchen (POST /review)": [
		{ "body": { "comment": "The pizza was amazing!", "rating": 5 }, "headers": {} }
	],
	"4. The Kitchen (GET /secret-dish)": [
		{ "body": {}, "headers": { "x-api-key": "super-secret-key" } }
	],
	"5. The Kitchen (GET /slow-service)": [{ "body": {}, "headers": {}, "query": {} }]
}
