{
    "type": "object",
    "properties": {
        "_embedded": {
            "type": "object",
            "properties": {
                "emails": {
                    "type": "array",
                    "items": {
                        "type": "object",
                        "properties": {
                            "id": {
                                "type": "integer"
                            },
                            "type": {
                                "type": "string"
                            },
                            "value": {
                                "type": "string"
                            }
                        }
                    }
                },
                "properties": {
                    "type": "array",
                    "items": {
                        "type": "object",
                        "properties": {
                            "name": {
                                "type": "string"
                            },
                            "slug": {
                                "type": "string"
                            },
                            "source": {
                                "type": "object",
                                "properties": {
                                    "name": {
                                        "type": "string"
                                    }
                                }
                            },
                            "text": {
                                "type": "string"
                            },
                            "type": {
                                "type": "string"
                            },
                            "value": {
                                "type": "string"
                            }
                        }
                    }
                }
            }
        },
        "_links": {
            "type": "object",
            "properties": {
                "address": {
                    "type": "object",
                    "properties": {
                        "href": {
                            "type": "string"
                        }
                    }
                },
                "chats": {
                    "type": "object",
                    "properties": {
                        "href": {
                            "type": "string"
                        }
                    }
                },
                "emails": {
                    "type": "object",
                    "properties": {
                        "href": {
                            "type": "string"
                        }
                    }
                },
                "phones": {
                    "type": "object",
                    "properties": {
                        "href": {
                            "type": "string"
                        }
                    }
                },
                "self": {
                    "type": "object",
                    "properties": {
                        "href": {
                            "type": "string"
                        }
                    }
                },
                "social-profiles": {
                    "type": "object",
                    "properties": {
                        "href": {
                            "type": "string"
                        }
                    }
                },
                "websites": {
                    "type": "object",
                    "properties": {
                        "href": {
                            "type": "string"
                        }
                    }
                }
            }
        },
        "background": {
            "type": "string"
        },
        "createdAt": {
            "type": "string"
        },
        "draft": {
            "type": "boolean"
        },
        "firstName": {
            "type": "string"
        },
        "gender": {
            "type": "string"
        },
        "id": {
            "type": "integer"
        },
        "jobTitle": {
            "type": "string"
        },
        "lastName": {
            "type": "string"
        },
        "photoType": {
            "type": "string"
        },
        "photoUrl": {
            "type": "string"
        },
        "updatedAt": {
            "type": "string"
        }
    },
    "version": 1
}
