{
	"node": "n8n-nodes-base.mandrill",
	"nodeVersion": "1.0",
	"codexVersion": "1.0",
	"categories": ["Communication", "Development"],
	"resources": {
		"credentialDocumentation": [
			{
				"url": "https://docs.n8n.io/integrations/builtin/credentials/mandrill/"
			}
		],
		"primaryDocumentation": [
			{
				"url": "https://docs.n8n.io/integrations/builtin/app-nodes/n8n-nodes-base.mandrill/"
			}
		],
		"generic": [
			{
				"label": "Love at first sight: Ricardo’s n8n journey",
				"icon": "❤️",
				"url": "https://n8n.io/blog/love-at-first-sight-ricardos-n8n-journey/"
			}
		]
	}
}
