{
	"id": "ministral-8b-latest",
	"name": "Ministral 8B (Latest)",
	"provider": "Mistral",
	"pricing": {
		"promptPerMilTokenUsd": 0.1,
		"completionPerMilTokenUsd": 0.1
	},
	"contextLength": 128000,
	"maxOutputTokens": 4096,
	"capabilities": {
		"functionCalling": true,
		"structuredOutput": false,
		"vision": false,
		"imageGeneration": false,
		"audio": false,
		"extendedThinking": false
	},
	"inputModalities": ["text"],
	"outputModalities": ["text"],
	"intelligenceLevel": "medium",
	"recommendedFor": ["conversation", "analysis", "function-calling"]
}
